interactions/ext/modmail/__init__.py
interactions/ext/modmail/modmail.py
interactions/ext/modmail/core/__init__.py
interactions/ext/modmail/core/_color_data.py
interactions/ext/modmail/core/config.json
interactions/ext/modmail/core/config.py
interactions/ext/modmail/core/models.py
interactions/ext/modmail/core/thread.py
interactions/ext/modmail/core/time.py
interactions/ext/modmail/core/utils.py
interactions_modmail-1.0.4.dist-info/LICENSE
interactions_modmail-1.0.4.dist-info/METADATA
interactions_modmail-1.0.4.dist-info/WHEEL
interactions_modmail-1.0.4.dist-info/top_level.txt
interactions_modmail-1.0.4.dist-info/RECORD
